datalookup/__init__.py
datalookup/_version.py
datalookup/exceptions.py
datalookup/fields.py
datalookup/lookup.py
datalookup/utils.py
datalookup-1.0.1.dist-info/AUTHORS
datalookup-1.0.1.dist-info/LICENCE
datalookup-1.0.1.dist-info/METADATA
datalookup-1.0.1.dist-info/WHEEL
datalookup-1.0.1.dist-info/top_level.txt
datalookup-1.0.1.dist-info/RECORD
