Metadata-Version: 2.1
Name: datalookup
Version: 1.0.1
Summary: Deep nested data filtering library
Author-email: Stephane Capponi <stephane.capponi@proton.me>
License: MIT
Project-URL: homepage, https://datalookup.readthedocs.io/en/latest/
Project-URL: repository, https://github.com/pyshare/datalookup
Project-URL: changelog, https://datalookup.readthedocs.io/en/latest/internals/changelog.html
Keywords: filter,dictionary,nested,datalookup,data-filtering,deep-filtering,lookup
Classifier: Development Status :: 5 - Production/Stable
Classifier: Intended Audience :: Developers
Classifier: License :: OSI Approved :: MIT License
Classifier: Operating System :: OS Independent
Classifier: Natural Language :: English
Classifier: Programming Language :: Python
Classifier: Programming Language :: Python :: 3
Classifier: Programming Language :: Python :: 3 :: Only
Classifier: Programming Language :: Python :: 3.9
Classifier: Topic :: Software Development :: Libraries
Classifier: Topic :: Software Development :: Libraries :: Python Modules
Classifier: Topic :: Utilities
Classifier: Typing :: Typed
Requires-Python: >=3.9
License-File: LICENCE
License-File: AUTHORS
